mathml2latex/__init__.py
mathml2latex/mathml.py
mathml2latex/parts_pickup.py
mathml2latex/process_each_tag/__init__.py
mathml2latex/process_each_tag/maligngroup.py
mathml2latex/process_each_tag/malignmark.py
mathml2latex/process_each_tag/math.py
mathml2latex/process_each_tag/mfenced.py
mathml2latex/process_each_tag/mfrac.py
mathml2latex/process_each_tag/mmultiscripts.py
mathml2latex/process_each_tag/mover.py
mathml2latex/process_each_tag/mpadded.py
mathml2latex/process_each_tag/mphantom.py
mathml2latex/process_each_tag/mroot.py
mathml2latex/process_each_tag/mrow.py
mathml2latex/process_each_tag/mspace.py
mathml2latex/process_each_tag/msqrt.py
mathml2latex/process_each_tag/mstyle.py
mathml2latex/process_each_tag/msub.py
mathml2latex/process_each_tag/msubsup.py
mathml2latex/process_each_tag/msup.py
mathml2latex/process_each_tag/mtable.py
mathml2latex/process_each_tag/mtd.py
mathml2latex/process_each_tag/mtext.py
mathml2latex/process_each_tag/mtr.py
mathml2latex/process_each_tag/munder.py
mathml2latex/process_each_tag/munderover.py
mathml2latex-0.2.12.dist-info/WHEEL
mathml2latex-0.2.12.dist-info/METADATA
mathml2latex-0.2.12.dist-info/RECORD
