Metadata-Version: 2.1
Name: mathml2latex
Version: 0.2.12
Summary: 
Home-page: https://github.com/KiaismAgre/mathml2latex
License: MIT
Author: KiaismAgre
Author-email: KUBOKAWA.Takara@nims.go.jp
Requires-Python: >=3.7,<4.0
Classifier: License :: OSI Approved :: MIT License
Classifier: Programming Language :: Python :: 3
Classifier: Programming Language :: Python :: 3.7
Requires-Dist: beautifulsoup4 (>=4.7,<5.0)
